unboxapi/__init__.py
unboxapi/api.py
unboxapi/datasets.py
unboxapi/exceptions.py
unboxapi/models.py
unboxapi/projects.py
unboxapi/schemas.py
unboxapi/tasks.py
unboxapi/utils.py
unboxapi/version.py
unboxapi-0.3.0.dist-info/LICENSE
unboxapi-0.3.0.dist-info/METADATA
unboxapi-0.3.0.dist-info/WHEEL
unboxapi-0.3.0.dist-info/top_level.txt
unboxapi-0.3.0.dist-info/RECORD
