Metadata-Version: 2.1
Name: unboxapi
Version: 0.3.0
Summary: The official Python API library for Unbox: the Testing and Debugging Platform for AI
Home-page: https://github.com/unboxai/unboxapi-python-client
Author: Unbox Inc.
Project-URL: Documentation, https://docs.unbox.ai/
Project-URL: Unbox User Slack Group, https://l.linklyhq.com/l/1DG73
Keywords: MLOps,AI,Unbox
Classifier: Operating System :: OS Independent
Classifier: Programming Language :: Python :: 3
Classifier: Programming Language :: Python :: 3 :: Only
Classifier: Programming Language :: Python :: 3.7
Classifier: Programming Language :: Python :: 3.8
Classifier: Programming Language :: Python :: 3.9
Classifier: Programming Language :: Python :: Implementation :: CPython
Classifier: Topic :: Scientific/Engineering :: Artificial Intelligence
Classifier: Topic :: Software Development :: Libraries
Requires-Python: >=3.7
License-File: LICENSE
Requires-Dist: bentoml (==0.13.1)
Requires-Dist: jupyter
Requires-Dist: pandas
Requires-Dist: requests
Requires-Dist: tqdm
Requires-Dist: marshmallow
Requires-Dist: protobuf (==3.20.0)
